<?xml version="1.0" encoding="UTF-8"?>
<objects serializationModel="Studio.01.08.00">
    <object class="AudioFile" id="{b2a4747f-3466-43ae-a9db-efa771ac6e22}">
        <property name="assetPath">
            <value>master_warning_old.wav</value>
        </property>
        <property name="frequencyInKHz">
            <value>44.0999985</value>
        </property>
        <property name="channelCount">
            <value>2</value>
        </property>
        <property name="length">
            <value>0.45043083900226755</value>
        </property>
        <relationship name="masterAssetFolder">
            <destination>{e26eb768-3a3a-41bf-8cc8-8bfd664eb35a}</destination>
        </relationship>
    </object>
</objects>
